{
  "cordialityList": [
    {
      "farmer": "Ellie",
      "npc": "Caroline",
      "point": 72.0
    },
    {
      "farmer": "Ellie",
      "npc": "Abigail",
      "point": 28.0
    },
    {
      "farmer": "Ellie",
      "npc": "Lewis",
      "point": 0.0
    },
    {
      "farmer": "Ellie",
      "npc": "George",
      "point": 0.0
    },
    {
      "farmer": "Ellie",
      "npc": "Haley",
      "point": 0.0
    },
    {
      "farmer": "Ellie",
      "npc": "MarlonFay",
      "point": 0.0
    },
    {
      "farmer": "Ellie",
      "npc": "Penny",
      "point": 48.0
    },
    {
      "farmer": "Ellie",
      "npc": "Linus",
      "point": 73.0
    },
    {
      "farmer": "Ellie",
      "npc": "Robin",
      "point": 2.0
    },
    {
      "farmer": "Ellie",
      "npc": "Sophia",
      "point": 0.0
    },
    {
      "farmer": "Ellie",
      "npc": "Flor",
      "point": 0.0
    },
    {
      "farmer": "Ellie",
      "npc": "Shane",
      "point": 22.0
    },
    {
      "farmer": "Ellie",
      "npc": "Emily",
      "point": 24.0
    },
    {
      "farmer": "Ellie",
      "npc": "Willy",
      "point": 0.0
    },
    {
      "farmer": "Ellie",
      "npc": "Leah",
      "point": 10.0
    },
    {
      "farmer": "Ellie",
      "npc": "Claire",
      "point": 10.0
    }
  ]
}